{"definitions": [{"wordtype": "Transitive Verb", "description": "To make heavy or heavier; to add to; to increase."}, {"wordtype": "Transitive Verb", "description": "To make worse, or more severe; to render less tolerable or less excusable; to make more offensive; to enhance; to intensify."}, {"wordtype": "Transitive Verb", "description": "To give coloring to in description; to exaggerate; as, to aggravate circumstances."}, {"wordtype": "Transitive Verb", "description": "To exasperate; to provoke; to irritate."}]}