{"definitions": [{"wordtype": "Noun", "description": "The act of giving form or shape to anything; a forming; a shaping."}, {"wordtype": "Noun", "description": "The manner in which a thing is formed; structure; construction; conformation; form; as, the peculiar formation of the heart."}, {"wordtype": "Noun", "description": "A substance formed or deposited."}, {"wordtype": "Noun", "description": "Mineral deposits and rock masses designated with reference to their origin; as, the siliceous formation about geysers; alluvial formations; marine formations."}, {"wordtype": "Noun", "description": "A group of beds of the same age or period; as, the Eocene formation."}, {"wordtype": "Noun", "description": "The arrangement of a body of troops, as in a square, column, etc."}]}