{"definitions": [{"wordtype": "Noun", "description": "The state of being free; exemption from the power and control of another; liberty; independence."}, {"wordtype": "Noun", "description": "Privileges; franchises; immunities."}, {"wordtype": "Noun", "description": "Exemption from necessity, in choise and action; as, the freedom of the will."}, {"wordtype": "Noun", "description": "Ease; facility; as, he speaks or acts with freedom."}, {"wordtype": "Noun", "description": "Frankness; openness; unreservedness."}, {"wordtype": "Noun", "description": "Improper familiarity; violation of the rules of decorum; license."}, {"wordtype": "Noun", "description": "Generosity; liberality."}]}