{"definitions": [{"wordtype": "Noun", "description": "Any large web-footen bird of the subfamily Anserinae, and belonging to Anser, Branta, Chen, and several allied genera. See Anseres."}, {"wordtype": "Noun", "description": "Any large bird of other related families, resembling the common goose."}, {"wordtype": "Noun", "description": "A tailor's smoothing iron, so called from its handle, which resembles the neck of a goose."}, {"wordtype": "Noun", "description": "A silly creature; a simpleton."}, {"wordtype": "Noun", "description": "A game played with counters on a board divided into compartments, in some of which a goose was depicted."}]}