{"definitions": [{"wordtype": "Plural", "description": "of Heathen"}, {"wordtype": "Noun", "description": "An individual of the pagan or unbelieving nations, or those which worship idols and do not acknowledge the true God; a pagan; an idolater."}, {"wordtype": "Noun", "description": "An irreligious person."}, {"wordtype": "Adjective", "description": "Gentile; pagan; as, a heathen author."}, {"wordtype": "Adjective", "description": "Barbarous; unenlightened; heathenish."}, {"wordtype": "Adjective", "description": "Irreligious; scoffing."}]}