{"definitions": [{"wordtype": "Transitive Verb", "description": "The place of the dead, or of souls after death; the grave; -- called in Hebrew sheol, and by the Greeks hades."}, {"wordtype": "Transitive Verb", "description": "The place or state of punishment for the wicked after death; the abode of evil spirits. Hence, any mental torment; anguish."}, {"wordtype": "Transitive Verb", "description": "A place where outcast persons or things are gathered"}, {"wordtype": "Transitive Verb", "description": "A dungeon or prison; also, in certain running games, a place to which those who are caught are carried for detention."}, {"wordtype": "Transitive Verb", "description": "A gambling house."}, {"wordtype": "Transitive Verb", "description": "A place into which a tailor throws his shreds, or a printer his broken type."}, {"wordtype": "Transitive Verb", "description": "To overwhelm."}]}