{"definitions": [{"wordtype": "Noun", "description": "A symbolical acknowledgment made by a feudal tenant to, and in the presence of, his lord, on receiving investiture of fee, or coming to it by succession, that he was his man, or vassal; profession of fealty to a sovereign."}, {"wordtype": "Noun", "description": "Respect or reverential regard; deference; especially, respect paid by external action; obeisance."}, {"wordtype": "Noun", "description": "Reverence directed to the Supreme Being; reverential worship; devout affection."}, {"wordtype": "Transitive Verb", "description": "To pay reverence to by external action."}, {"wordtype": "Transitive Verb", "description": "To cause to pay homage."}]}