{"definitions": [{"wordtype": "Transitive Verb", "description": "To meet with violence or shock; to clash; to jostle."}, {"wordtype": "Transitive Verb", "description": "To move rapidly; to wheel or rush suddenly or with violence; to whirl round rapidly; to skirmish."}, {"wordtype": "Transitive Verb", "description": "To make a threatening sound, like the clash of arms; to make a sound as of confused clashing or confusion; to resound."}, {"wordtype": "Transitive Verb", "description": "To move with violence or impetuosity; to whirl; to brandish."}, {"wordtype": "Transitive Verb", "description": "To push; to jostle; to hurl."}]}