{"definitions": [{"wordtype": "Noun", "description": "The quality or condition of being a neighbor; the state of being or dwelling near; proximity."}, {"wordtype": "Noun", "description": "A place near; vicinity; adjoining district; a region the inhabitants of which may be counted as neighbors; as, he lives in my neighborhood."}, {"wordtype": "Noun", "description": "The inhabitants who live in the vicinity of each other; as, the fire alarmed all the neiborhood."}, {"wordtype": "Noun", "description": "The disposition becoming a neighbor; neighborly kindness or good will."}]}