{"definitions": [{"wordtype": "Verb", "description": "move or cause to move in a specified direction"}, {"wordtype": "Verb", "description": "go past or across; leave behind or on one side in proceeding"}, {"wordtype": "Verb", "description": "(of time) elapse; go by"}, {"wordtype": "Verb", "description": "transfer (something) to someone, especially by handing or bequeathing it to the next person in a series"}, {"wordtype": "Verb", "description": "(of a candidate) be successful in (an examination, test, or course)"}, {"wordtype": "Verb", "description": "(of a legislative or other official body) approve or put into effect (a proposal or law) by voting on it"}, {"wordtype": "Verb", "description": "pronounce (a judgement or judicial sentence)"}, {"wordtype": "Verb", "description": "discharge (something, especially urine or faeces) from the body"}, {"wordtype": "Verb", "description": "forgo one's turn in a game or an offered opportunity to do or have something"}]}