{"definitions": [{"wordtype": "Noun", "description": "the ability or capacity to do something or act in a particular way"}, {"wordtype": "Noun", "description": "the capacity or ability to direct or influence the behaviour of others or the course of events"}, {"wordtype": "Noun", "description": "physical strength and force exerted by something or someone"}, {"wordtype": "Noun", "description": "energy that is produced by mechanical, electrical, or other means and used to operate a device"}, {"wordtype": "Noun", "description": "the rate of doing work, measured in watts or less frequently horse power."}, {"wordtype": "Noun", "description": "the product obtained when a number is multiplied by itself a certain number of times"}, {"wordtype": "Noun", "description": "a large number or amount of something"}]}