{"definitions": [{"wordtype": "Transitive Verb", "description": "To mark again, or a second time; to mark anew."}, {"wordtype": "Noun", "description": "To mark in a notable manner; to distinquish clearly; to make noticeable or conspicuous; to piont out."}, {"wordtype": "Noun", "description": "To take notice of, or to observe, mentally; as, to remark the manner of a speaker."}, {"wordtype": "Noun", "description": "To express in words or writing, as observed or noticed; to state; to say; -- often with a substantive clause; as, he remarked that it was time to go."}, {"wordtype": "Verb Intransitive", "description": "To make a remark or remarks; to comment."}, {"wordtype": "Noun", "description": "Act of remarking or attentively noticing; notice or observation."}, {"wordtype": "Noun", "description": "The expression, in speech or writing, of something remarked or noticed; the mention of that which is worthy of attention or notice; hence, also, a casual observation, comment, or statement; as, a pertinent remark."}]}