{"definitions": [{"wordtype": "Adjective", "description": "Having a bay, chestnut, brown, or black color, with gray or white thickly interspersed; -- said of a horse."}, {"wordtype": "Adjective", "description": "Made of the leather called roan; as, roan binding."}, {"wordtype": "Noun", "description": "The color of a roan horse; a roan color."}, {"wordtype": "Noun", "description": "A roan horse."}, {"wordtype": "Noun", "description": "A kind of leather used for slippers, bookbinding, etc., made from sheepskin, tanned with sumac and colored to imitate ungrained morocco."}]}