{"definitions": [{"wordtype": "Noun", "description": "a point, period, or step in a process or development"}, {"wordtype": "Noun", "description": "a raised floor or platform, typically in a theatre, on which actors, entertainers, or speakers perform"}, {"wordtype": "Noun", "description": "a floor or level of a building or structure"}, {"wordtype": "Noun", "description": "(in chronostratigraphy) a range of strata corresponding to an age in time, forming a subdivision of a series"}, {"wordtype": "Noun", "description": "a stagecoach."}]}