{"definitions": [{"wordtype": "Noun", "description": "the highest or uppermost point, part, or surface of something"}, {"wordtype": "Noun", "description": "a lid, cover, or cap"}, {"wordtype": "Noun", "description": "the highest or most important rank, level, or position"}, {"wordtype": "Noun", "description": "a garment covering the upper part of the body and worn with a skirt, trousers, or shorts"}, {"wordtype": "Noun", "description": "the end of something that is furthest from the speaker or a point of reference"}, {"wordtype": "Noun", "description": "a bundle of long wool fibres prepared for spinning."}, {"wordtype": "Noun", "description": "a man who takes the active role in anal intercourse with another man."}]}