{"definitions": [{"wordtype": "Adjective", "description": "Having one meaning only; -- contrasted with equivocal."}, {"wordtype": "Adjective", "description": "Having unison of sound, as the octave in music. See Unison, n., 2."}, {"wordtype": "Noun", "description": "Having always the same drift or tenor; uniform; certain; regular."}, {"wordtype": "Noun", "description": "Unequivocal; indubitable."}, {"wordtype": "Noun", "description": "A generic term, or a term applicable in the same sense to all the species it embraces."}, {"wordtype": "Noun", "description": "A word having but one meaning."}]}